kymang/__init__.py
kymang/client.py
kymang/dispatcher.py
kymang/emoji.py
kymang/file_id.py
kymang/filters.py
kymang/mime_types.py
kymang/py.typed
kymang/sync.py
kymang/utils.py
kymang/connection/__init__.py
kymang/connection/connection.py
kymang/connection/transport/__init__.py
kymang/connection/transport/tcp/__init__.py
kymang/connection/transport/tcp/tcp.py
kymang/connection/transport/tcp/tcp_abridged.py
kymang/connection/transport/tcp/tcp_abridged_o.py
kymang/connection/transport/tcp/tcp_full.py
kymang/connection/transport/tcp/tcp_intermediate.py
kymang/connection/transport/tcp/tcp_intermediate_o.py
kymang/crypto/__init__.py
kymang/crypto/aes.py
kymang/crypto/mtproto.py
kymang/crypto/prime.py
kymang/crypto/rsa.py
kymang/enums/__init__.py
kymang/enums/auto_name.py
kymang/enums/chat_action.py
kymang/enums/chat_event_action.py
kymang/enums/chat_member_status.py
kymang/enums/chat_members_filter.py
kymang/enums/chat_type.py
kymang/enums/message_entity_type.py
kymang/enums/message_media_type.py
kymang/enums/message_service_type.py
kymang/enums/messages_filter.py
kymang/enums/next_code_type.py
kymang/enums/parse_mode.py
kymang/enums/poll_type.py
kymang/enums/sent_code_type.py
kymang/enums/user_status.py
kymang/errors/__init__.py
kymang/errors/rpc_error.py
kymang/handlers/__init__.py
kymang/handlers/callback_query_handler.py
kymang/handlers/chat_join_request_handler.py
kymang/handlers/chat_member_updated_handler.py
kymang/handlers/chosen_inline_result_handler.py
kymang/handlers/conversation_handler.py
kymang/handlers/deleted_messages_handler.py
kymang/handlers/disconnect_handler.py
kymang/handlers/edited_message_handler.py
kymang/handlers/handler.py
kymang/handlers/inline_query_handler.py
kymang/handlers/message_handler.py
kymang/handlers/poll_handler.py
kymang/handlers/raw_update_handler.py
kymang/handlers/user_status_handler.py
kymang/helpers/__init__.py
kymang/helpers/helpers.py
kymang/methods/__init__.py
kymang/methods/advanced/__init__.py
kymang-0.0.2.dist-info/COPYING
kymang-0.0.2.dist-info/COPYING.lesser
kymang-0.0.2.dist-info/METADATA
kymang-0.0.2.dist-info/NOTICE
kymang-0.0.2.dist-info/WHEEL
kymang-0.0.2.dist-info/top_level.txt
kymang-0.0.2.dist-info/RECORD
