Metadata-Version: 2.1
Name: kymang
Version: 0.0.2
Summary: kymang - Telegram MTProto API Client Library for Python.
Home-page: https://github.com/kymang/kymang
Author: Dan
Author-email: dan@pyrogram.org
License: LGPLv3
Download-URL: https://github.com/kymang/kymang
Project-URL: Tracker, https://github.com/kymang/kymang/issues
Project-URL: Community, https://t.me/kynansupport
Project-URL: Source, https://github.com/kymang/kymang
Project-URL: Documentation, https://docs.kymang.org
Keywords: telegram chat messenger mtproto api client library python
Platform: UNKNOWN
Classifier: Development Status :: 5 - Production/Stable
Classifier: Intended Audience :: Developers
Classifier: Natural Language :: English
Classifier: License :: OSI Approved :: GNU Lesser General Public License v3 (LGPLv3)
Classifier: Operating System :: OS Independent
Classifier: Programming Language :: Python
Classifier: Programming Language :: Python :: 3
Classifier: Programming Language :: Python :: 3.7
Classifier: Programming Language :: Python :: 3.8
Classifier: Programming Language :: Python :: 3.9
Classifier: Programming Language :: Python :: 3.10
Classifier: Programming Language :: Python :: 3.11
Classifier: Programming Language :: Python :: Implementation
Classifier: Programming Language :: Python :: Implementation :: CPython
Classifier: Programming Language :: Python :: Implementation :: PyPy
Classifier: Topic :: Internet
Classifier: Topic :: Communications
Classifier: Topic :: Communications :: Chat
Classifier: Topic :: Software Development :: Libraries
Classifier: Topic :: Software Development :: Libraries :: Python Modules
Classifier: Topic :: Software Development :: Libraries :: Application Frameworks
Requires-Python: ~=3.7
License-File: COPYING
License-File: COPYING.lesser
License-File: NOTICE
Requires-Dist: aiohttp (==3.8.5)
Requires-Dist: aiosqlite (<0.18.0,>=0.16.0)
Requires-Dist: motor (==3.2.0)
Requires-Dist: pyaes (==1.6.1)
Requires-Dist: pymongo (==4.4.1)
Requires-Dist: pysocks (==1.7.1)
Requires-Dist: pyyaml (==6.0.1)
Requires-Dist: screeninfo
